disco_tools-0.1.2.dist-info/licenses/LICENSE
tools/__init__.py
tools/_version.py
tools/ctypes.py
tools/label_selector/__init__.py
tools/label_selector/core.py
tools/label_selector/label.py
tools/label_selector/rule.py
tools/mp_logging/__init__.py
tools/mp_logging/core.py
disco_tools-0.1.2.dist-info/METADATA
disco_tools-0.1.2.dist-info/WHEEL
disco_tools-0.1.2.dist-info/top_level.txt
disco_tools-0.1.2.dist-info/RECORD
