Metadata-Version: 2.4
Name: disco-tools
Version: 0.1.2
Summary: Common tools for disco simulation engine.
Author: Michiel Jansen
License: MIT
Classifier: License :: OSI Approved :: MIT License
Classifier: Programming Language :: Python :: 3 :: Only
Classifier: Programming Language :: Python :: 3.11
Classifier: Programming Language :: Python :: 3.12
Classifier: Programming Language :: Python :: 3.13
Classifier: Operating System :: OS Independent
Requires-Python: >=3.11
License-File: LICENSE
Requires-Dist: numpy>=1.23
Requires-Dist: pyyaml>=6.0
Provides-Extra: dev
Requires-Dist: pytest>=8; extra == "dev"
Requires-Dist: pytest-cov>=5; extra == "dev"
Requires-Dist: mypy>=1.10; extra == "dev"
Requires-Dist: twine>=5; extra == "dev"
Requires-Dist: types-pyyaml>=6.0; extra == "dev"
Dynamic: license-file
